Metadata-Version: 1.1
Name: pywscat
Version: 0.1
Summary: Simple Websocket Netcat thing
Home-page: https://github.com/bannsec/wscat
Author: Michael Bann
Author-email: self@bannsecurity.com
License: MIT
Keywords: python3 websockets netcat
Platform: UNKNOWN
Classifier: Development Status :: 3 - Alpha
Classifier: Intended Audience :: End Users/Desktop
Classifier: License :: OSI Approved :: MIT License
Classifier: Programming Language :: Python :: 3
Classifier: Operating System :: POSIX :: Linux
Classifier: Environment :: Console
